baclns/__init__.py
baclns/controller.py
baclns/plotting.py
baclns/saving.py
baclns/simulation.py
BaCLNS-0.1.1.dist-info/LICENSE
BaCLNS-0.1.1.dist-info/METADATA
BaCLNS-0.1.1.dist-info/WHEEL
BaCLNS-0.1.1.dist-info/top_level.txt
BaCLNS-0.1.1.dist-info/RECORD
