Metadata-Version: 2.1
Name: BaCLNS
Version: 0.1.1
Summary: Efficient Backstepping Control for Linear and Nonlinear Dynamic Systems
Home-page: https://github.com/sof-danny/BaCLNS
Author: Samuel O. Folorunsho
Author-email: folorunshosamuel001@gmail.com
Classifier: Programming Language :: Python :: 3
Classifier: License :: OSI Approved :: MIT License
Classifier: Operating System :: OS Independent
Requires-Python: >=3.6
License-File: LICENSE
Requires-Dist: numpy
Requires-Dist: sympy
Requires-Dist: matplotlib
